client.py
note0-0.1.0.dist-info/DESCRIPTION.rst
note0-0.1.0.dist-info/METADATA
note0-0.1.0.dist-info/RECORD
note0-0.1.0.dist-info/WHEEL
note0-0.1.0.dist-info/entry_points.txt
note0-0.1.0.dist-info/metadata.json
note0-0.1.0.dist-info/top_level.txt
