Metadata-Version: 2.0
Name: note0
Version: 0.1.0
Summary: A command line note taking application
Home-page: https://github.com/ajay0/note0
Author: UNKNOWN
Author-email: UNKNOWN
License: MIT
Platform: UNKNOWN
Classifier: License :: OSI Approved :: MIT License
Classifier: Programming Language :: Python :: 3.5
Requires-Dist: requests
